pyiris_iceberg/__init__.py
pyiris_iceberg/api.py
pyiris_iceberg/app.py
pyiris_iceberg/main.py
pyiris_iceberg/utils.py
tests/__init__.py
tests/fixtures/testing_configs.py
tests/unit/__init__.py
tests/unit/test_main.py
pyiris_iceberg-1.0.dist-info/METADATA
pyiris_iceberg-1.0.dist-info/WHEEL
pyiris_iceberg-1.0.dist-info/entry_points.txt
pyiris_iceberg-1.0.dist-info/top_level.txt
pyiris_iceberg-1.0.dist-info/RECORD
